[
    {
        "pk": 1,
        "model": "funding_programs.fundingprogram",
        "fields": {
            "concession_year": 2012,
            "short_name": "INNPACTO 2012",
            "geographical_scope": "Spain",
            "observations": null,
            "full_name": "Convocatoria INNPACTO 2012",
            "organization": 2,
            "logo": "",
            "slug": "innpacto-2012"
        }
    },
    {
        "pk": 2,
        "model": "funding_programs.fundingprogram",
        "fields": {
            "concession_year": 2012,
            "short_name": "GAITEK 2012",
            "geographical_scope": "Euskadi",
            "observations": "3f90ap kpe\u00e7kcfj ue fdjl\u00f1akj3v j",
            "full_name": "GAITEK 2012",
            "organization": 8,
            "logo": "",
            "slug": "gaitek-2012"
        }
    },
    {
        "pk": 3,
        "model": "funding_programs.fundingprogram",
        "fields": {
            "concession_year": 2012,
            "short_name": "ETORTEK 2012",
            "geographical_scope": "Euskadi",
            "observations": null,
            "full_name": "Programa ETORTEK 2012",
            "organization": 8,
            "logo": "",
            "slug": "etortek-2012"
        }
    },
    {
        "pk": 4,
        "model": "funding_programs.fundingprogram",
        "fields": {
            "concession_year": 2011,
            "short_name": "FP7-ICT-2011-8",
            "geographical_scope": "Europe",
            "observations": null,
            "full_name": "FP7-ICT-2011-8, Nr. 317601 (AAL-2012-5-187)",
            "organization": 22,
            "logo": "",
            "slug": "fp7-ict-2011-8"
        }
    },
    {
        "pk": 5,
        "model": "funding_programs.fundingprogram",
        "fields": {
            "concession_year": 2012,
            "short_name": "CIP-ICT-PSP-2012-6",
            "geographical_scope": "Europe",
            "observations": null,
            "full_name": "CIP-ICT-PSP-2012-6, de modalidad Pilot Type B",
            "organization": 22,
            "logo": "",
            "slug": "cip-ict-psp-2012-6"
        }
    },
    {
        "pk": 6,
        "model": "funding_programs.fundingprogram",
        "fields": {
            "concession_year": 2011,
            "short_name": "INNPACTO 2011",
            "geographical_scope": "Spain",
            "observations": null,
            "full_name": "INNPACTO 2011, IPT-2011-1052-390000  ",
            "organization": 2,
            "logo": "",
            "slug": "innpacto-2011"
        }
    },
    {
        "pk": 7,
        "model": "funding_programs.fundingprogram",
        "fields": {
            "concession_year": 2011,
            "short_name": "ETORGAI 2011",
            "geographical_scope": "Euskadi",
            "observations": null,
            "full_name": "Programa ETORGAI 2011, ER-2011/00018 ",
            "organization": 8,
            "logo": "",
            "slug": "etorgai-2011"
        }
    },
    {
        "pk": 8,
        "model": "funding_programs.fundingprogram",
        "fields": {
            "concession_year": 2012,
            "short_name": "PC2012-73A",
            "geographical_scope": "Euskadi",
            "observations": null,
            "full_name": "Proyectos de Investigaci\u00f3n B\u00e1sica y/o Aplicada, Proyectos en Cooperaci\u00f3n y Proyectos en Humanidades y Ciencias Sociales",
            "organization": 8,
            "logo": "",
            "slug": "pc2012-73a"
        }
    },
    {
        "pk": 9,
        "model": "funding_programs.fundingprogram",
        "fields": {
            "concession_year": 2011,
            "short_name": "ETORTEK 2011",
            "geographical_scope": "Euskadi",
            "observations": null,
            "full_name": "Programa ETORTEK 2011, Departamento de Industria, Innovaci\u00f3n, Comercio y Turismo, IE11-316 ",
            "organization": 8,
            "logo": "",
            "slug": "etortek-2011"
        }
    },
    {
        "pk": 10,
        "model": "funding_programs.fundingprogram",
        "fields": {
            "concession_year": 2010,
            "short_name": "CENIT 2010",
            "geographical_scope": "Spain",
            "observations": null,
            "full_name": "CENIT 2010",
            "organization": 2,
            "logo": "",
            "slug": "cenit-2010"
        }
    },
    {
        "pk": 11,
        "model": "funding_programs.fundingprogram",
        "fields": {
            "concession_year": 2008,
            "short_name": "TIN 2010",
            "geographical_scope": "Spain",
            "observations": null,
            "full_name": "PLAN NACIONAL de I+D+i 2008-2011, Subprograma de Proyectos de Investigaci\u00f3n Fundamental (TIN2010-20510-C04-03)",
            "organization": 2,
            "logo": "",
            "slug": "tin-2010"
        }
    },
    {
        "pk": 12,
        "model": "funding_programs.fundingprogram",
        "fields": {
            "concession_year": 2010,
            "short_name": "ITEA 2",
            "geographical_scope": "Spain",
            "observations": null,
            "full_name": "MINISTERIO DE INDUSTRIA, TURISMO Y COMERCIO, TSI-020400-2010-100, ITEA2",
            "organization": 1,
            "logo": "",
            "slug": "itea-2"
        }
    },
    {
        "pk": 13,
        "model": "funding_programs.fundingprogram",
        "fields": {
            "concession_year": 2010,
            "short_name": "ETORGAI 2010",
            "geographical_scope": "Euskadi",
            "observations": null,
            "full_name": "ETORGAI 2010",
            "organization": 8,
            "logo": "",
            "slug": "etorgai-2010"
        }
    },
    {
        "pk": 14,
        "model": "funding_programs.fundingprogram",
        "fields": {
            "concession_year": 2010,
            "short_name": "SAIOTEK 2010",
            "geographical_scope": "Euskadi",
            "observations": null,
            "full_name": "SAIOTEK 2010",
            "organization": 8,
            "logo": "",
            "slug": "saiotek-2010"
        }
    },
    {
        "pk": 15,
        "model": "funding_programs.fundingprogram",
        "fields": {
            "concession_year": 2010,
            "short_name": "GAITEK 2010",
            "geographical_scope": "Euskadi",
            "observations": null,
            "full_name": "GAITEK-INTEK 2010",
            "organization": 8,
            "logo": "",
            "slug": "gaitek-2010"
        }
    },
    {
        "pk": 16,
        "model": "funding_programs.fundingprogram",
        "fields": {
            "concession_year": 2011,
            "short_name": "GAITEK 2011",
            "geographical_scope": "Euskadi",
            "observations": null,
            "full_name": "GAITEK-INTEK 2011",
            "organization": 8,
            "logo": "",
            "slug": "gaitek-2011"
        }
    },
    {
        "pk": 17,
        "model": "funding_programs.fundingprogram",
        "fields": {
            "concession_year": 2010,
            "short_name": "ETORTEK 2010",
            "geographical_scope": "Euskadi",
            "observations": null,
            "full_name": "ETORTEK 2010",
            "organization": 8,
            "logo": "",
            "slug": "etortek-2010"
        }
    },
    {
        "pk": 18,
        "model": "funding_programs.fundingprogram",
        "fields": {
            "concession_year": 2011,
            "short_name": "BIZKAILAB 2011",
            "geographical_scope": "Bizkaia",
            "observations": null,
            "full_name": "BIZKAILAB 2011",
            "organization": 8,
            "logo": "",
            "slug": "bizkailab-2011"
        }
    },
    {
        "pk": 19,
        "model": "funding_programs.fundingprogram",
        "fields": {
            "concession_year": 2012,
            "short_name": "GAITEK 2012",
            "geographical_scope": "Euskadi",
            "observations": null,
            "full_name": "GAITEK-INTEK 2012",
            "organization": 8,
            "logo": "",
            "slug": "gaitek-2012"
        }
    },
    {
        "pk": 20,
        "model": "funding_programs.fundingprogram",
        "fields": {
            "concession_year": 2007,
            "short_name": "GALILEO 2007",
            "geographical_scope": "Spain",
            "observations": null,
            "full_name": "FP7, GALILEO-2007-GSA-1",
            "organization": 2,
            "logo": "",
            "slug": "galileo-2007"
        }
    }
]